stockinfoain1001/__init__.py
stockinfoain1001/stockinfoain1001.py
stockinfoain1001-1.0.2.dist-info/LICENSE
stockinfoain1001-1.0.2.dist-info/METADATA
stockinfoain1001-1.0.2.dist-info/WHEEL
stockinfoain1001-1.0.2.dist-info/top_level.txt
stockinfoain1001-1.0.2.dist-info/RECORD
