Metadata-Version: 2.1
Name: stockinfoain1001
Version: 1.0.2
Summary: Stock information analysis package
Author: Abdurrahman Javat
Author-email: <abdurrahman.javat@bahcesehir.edu.tr>
Keywords: python,stock,finance,SMA,RSI
Classifier: Programming Language :: Python :: 3
Classifier: Operating System :: OS Independent
License-File: LICENSE
